{"version":1,"resource":"file:///c%3A/JUNGHO/10.VScode/Microsoft%20VS%20Code/1.Workspace/jsp_work/src/main/webapp/jsdk.jsp","entries":[{"id":"T2bs.jsp","timestamp":1671190443463},{"id":"cWIo.jsp","source":"moved.source","timestamp":1671190480335},{"id":"zzea.jsp","timestamp":1671190510176},{"id":"icgj.jsp","source":"moved.source","timestamp":1671190564470},{"id":"YCJO.jsp","timestamp":1671411806547},{"id":"Vx2B.jsp","timestamp":1671413927759},{"id":"3wEE.jsp","source":"undoRedo.source","timestamp":1671413929390},{"id":"rWX9.jsp","timestamp":1671413932101}]}